OpenGL/__init__.py
OpenGL/_bytes.py
OpenGL/_configflags.py
OpenGL/_null.py
OpenGL/_opaque.py
OpenGL/acceleratesupport.py
OpenGL/constant.py
OpenGL/constants.py
OpenGL/contextdata.py
OpenGL/converters.py
OpenGL/error.py
OpenGL/extensions.py
OpenGL/images.py
OpenGL/latebind.py
OpenGL/lazywrapper.py
OpenGL/logs.py
OpenGL/plugins.py
OpenGL/version.py
OpenGL/wrapper.py
OpenGL/AGL/__init__.py
OpenGL_glut-0.0.3.dist-info/METADATA
OpenGL_glut-0.0.3.dist-info/WHEEL
OpenGL_glut-0.0.3.dist-info/top_level.txt
OpenGL_glut-0.0.3.dist-info/RECORD
