Metadata-Version: 2.1
Name: OpenGL-glut
Version: 0.0.3
Summary: OpenGL with glut support
Author-email: Ruud van der Ham <rt.van.der.ham@gmail.com>
Project-URL: Homepage, https://github.com/salabim/opengl
Project-URL: Repository, https://github.com/salabim/opengl
Classifier: Development Status :: 5 - Production/Stable
Classifier: License :: OSI Approved :: MIT License
Classifier: Programming Language :: Python :: 3 :: Only
Requires-Python: >=3.7
